ncbi_geo_pubmed/__init__.py
ncbi_geo_pubmed/cli.py
ncbi_geo_pubmed/config.py
ncbi_geo_pubmed/core.py
ncbi_geo_pubmed/exceptions.py
ncbi_geo_pubmed/search.py
ncbi_geo_pubmed/utils.py
ncbi_geo_pubmed_search-1.0.0.dist-info/licenses/LICENSE
ncbi_geo_pubmed_search-1.0.0.dist-info/METADATA
ncbi_geo_pubmed_search-1.0.0.dist-info/WHEEL
ncbi_geo_pubmed_search-1.0.0.dist-info/entry_points.txt
ncbi_geo_pubmed_search-1.0.0.dist-info/top_level.txt
ncbi_geo_pubmed_search-1.0.0.dist-info/RECORD
