Metadata-Version: 2.4
Name: ncbi-geo-pubmed-search
Version: 1.0.0
Summary: A powerful Python package for searching NCBI GEO and PubMed databases with advanced filtering
Home-page: https://github.com/mdbabumiamssm/ncbi-geo-pubmed-search
Author: MD BABU MIA, PHD
Author-email: Your Name <your.email@example.com>
License: MIT
Project-URL: Homepage, https://github.com/yourusername/ncbi-geo-pubmed-search
Project-URL: Documentation, https://github.com/yourusername/ncbi-geo-pubmed-search#readme
Project-URL: Repository, https://github.com/yourusername/ncbi-geo-pubmed-search
Project-URL: Issues, https://github.com/yourusername/ncbi-geo-pubmed-search/issues
Classifier: Development Status :: 4 - Beta
Classifier: Intended Audience :: Science/Research
Classifier: License :: OSI Approved :: MIT License
Classifier: Programming Language :: Python :: 3
Classifier: Programming Language :: Python :: 3.7
Classifier: Programming Language :: Python :: 3.8
Classifier: Programming Language :: Python :: 3.9
Classifier: Programming Language :: Python :: 3.10
Classifier: Programming Language :: Python :: 3.11
Requires-Python: >=3.7
License-File: LICENSE
Requires-Dist: biopython>=1.79
Requires-Dist: pandas>=1.3.0
Requires-Dist: openpyxl>=3.0.9
Requires-Dist: requests>=2.25.0
Provides-Extra: dev
Requires-Dist: pytest>=6.0; extra == "dev"
Requires-Dist: pytest-cov>=2.0; extra == "dev"
Requires-Dist: black>=22.0; extra == "dev"
Requires-Dist: flake8>=4.0; extra == "dev"
Requires-Dist: mypy>=0.910; extra == "dev"
Requires-Dist: sphinx>=4.0; extra == "dev"
Dynamic: author
Dynamic: home-page
Dynamic: license-file
Dynamic: requires-python
